aind_anatomical_utils/__init__.py
aind_anatomical_utils/anatomical_volume.py
aind_anatomical_utils/ants_volume.py
aind_anatomical_utils/coordinate_systems.py
aind_anatomical_utils/py.typed
aind_anatomical_utils/sitk_volume.py
aind_anatomical_utils/slicer.py
aind_anatomical_utils/utils.py
aind_anatomical_utils-0.4.2.dist-info/licenses/LICENSE
aind_anatomical_utils-0.4.2.dist-info/METADATA
aind_anatomical_utils-0.4.2.dist-info/WHEEL
aind_anatomical_utils-0.4.2.dist-info/top_level.txt
aind_anatomical_utils-0.4.2.dist-info/RECORD
