Metadata-Version: 2.4
Name: aind-anatomical-utils
Version: 0.4.2
Summary: Tools to work with anatomically-aware files
Author: Allen Institute for Neural Dynamics
Author-email: Galen Lynch <galen@galenlynch.com>, Yoni Browning <yoni.browning@alleninstitute.org>
License-Expression: MIT
Project-URL: Repository, https://github.com/AllenNeuralDynamics/aind-anatomical-utils/
Project-URL: Issues, https://github.com/AllenNeuralDynamics/aind-anatomical-utils/issues
Project-URL: Changelog, https://github.com/AllenNeuralDynamics/aind-anatomical-utils/blob/main/CHANGELOG.md
Classifier: Programming Language :: Python :: 3
Requires-Python: >=3.9
License-File: LICENSE
Requires-Dist: numpy<3,>=1.7
Requires-Dist: SimpleITK<3,>=2
Requires-Dist: antspyx<0.7,>=0.6
Dynamic: license-file
